{
    "players": {
        "ivan": {
            "pveWins": 2,
            "bestWinStreak": 2,
            "currentWinStreak": 2,
            "shots": 154,
            "hits": 58,
            "fastestWinTurns": 74
        },
        "kevin": {
            "pveWins": 2,
            "bestWinStreak": 2,
            "currentWinStreak": 2,
            "shots": 146,
            "hits": 58,
            "fastestWinTurns": 61
        },
        "benji": {
            "pveWins": 1,
            "bestWinStreak": 1,
            "currentWinStreak": 1,
            "shots": 61,
            "hits": 29,
            "fastestWinTurns": 61
        }
    }
}